YahooFinanceSpider/__init__.py
YahooFinanceSpider/data_type.py
YahooFinanceSpider/get_brand_info.py
YahooFinanceSpider/get_price.py
YahooFinanceSpider-0.3.dist-info/METADATA
YahooFinanceSpider-0.3.dist-info/RECORD
YahooFinanceSpider-0.3.dist-info/WHEEL
YahooFinanceSpider-0.3.dist-info/top_level.txt
