Metadata-Version: 2.1
Name: YahooFinanceSpider
Version: 0.3
Summary: A crawler of YahooFinace's Stock
Home-page: https://github.com/S-W-K/YahooFinaceSpider
Author: S-W-K
Author-email: s979612095@gmail.com
License: UNKNOWN
Keywords: japanese yahoo stock finance investment
Platform: UNKNOWN
Classifier: Programming Language :: Python :: 3
Classifier: License :: OSI Approved :: MIT License
Classifier: Operating System :: OS Independent
Requires-Dist: lxml
Requires-Dist: requests
Requires-Dist: fake-useragent
